agent_smith_ai/__init__.py
agent_smith_ai/bash_agent/__init__.py
agent_smith_ai/bash_agent/agent/__init__.py
agent_smith_ai/bash_agent/agent/bashai_agent.py
agent_smith_ai/bash_agent/config/__init__.py
agent_smith_ai/bash_agent/config/init.py
agent_smith_ai/bash_agent/config/profiles.py
agent_smith_ai/bash_agent/main.py
agent_smith_ai/bash_agent/utils/__init__.py
agent_smith_ai/bash_agent/utils/conversation_log.py
agent_smith_ai/cli_agent.py
agent_smith_ai/models.py
agent_smith_ai/openapi_wrapper.py
agent_smith_ai/streamlit_server.py
agent_smith_ai/token_bucket.py
agent_smith_ai/utility_agent.py
agent_smith_ai-1.0.1.dist-info/LICENSE
agent_smith_ai-1.0.1.dist-info/METADATA
agent_smith_ai-1.0.1.dist-info/WHEEL
agent_smith_ai-1.0.1.dist-info/RECORD
