Metadata-Version: 2.1
Name: agent-smith-ai
Version: 1.0.1
Summary: agent-smith-ai
License: MIT
Author: Shawn T. O'Neil
Author-email: shawn@tislab.org
Requires-Python: >=3.9, !=2.7.*, !=3.0.*, !=3.1.*, !=3.2.*, !=3.3.*, !=3.4.*, !=3.5.*, !=3.6.*, !=3.7.*, !=3.8.*
Classifier: License :: OSI Approved :: MIT License
Classifier: Programming Language :: Python :: 3
Classifier: Programming Language :: Python :: 3.9
Classifier: Programming Language :: Python :: 3.10
Classifier: Programming Language :: Python :: 3.11
Provides-Extra: tests
Requires-Dist: asteval (>=0.9.29,<0.10.0)
Requires-Dist: autodoc-pydantic (>=2.0.1,<3.0.0)
Requires-Dist: click
Requires-Dist: colorama (>=0.4.6,<0.5.0)
Requires-Dist: docstring-parser (>=0.15,<0.16)
Requires-Dist: fastapi (>=0.101.1,<0.102.0)
Requires-Dist: httpx (>=0.24.1,<0.25.0)
Requires-Dist: importlib-metadata (>=4.8.0,<5.0.0)
Requires-Dist: openai (>=0.27.7,<0.28.0)
Requires-Dist: prompt-toolkit (>=3.0.38,<4.0.0)
Requires-Dist: pydantic (>=2.1.1,<3.0.0)
Requires-Dist: pytest (>=7.3.1,<8.0.0) ; extra == "tests"
Requires-Dist: python-dotenv (>=1.0.0,<2.0.0)
Requires-Dist: rich (>=13.4.2,<14.0.0)
Requires-Dist: sphinx-autodoc-typehints (>=1.24.0,<2.0.0)
Requires-Dist: sphinx-rtd-theme (==1.3.0rc1)
Requires-Dist: streamlit (>=1.26.0,<2.0.0)
Requires-Dist: tiktoken (>=0.4.0,<0.5.0)
Requires-Dist: toml (>=0.10.2,<0.11.0)
Requires-Dist: twine (>=4.0.2,<5.0.0)
Requires-Dist: uvicorn (>=0.23.2,<0.24.0)
Requires-Dist: websockets (>=11.0.3,<12.0.0)
